<?xml version="1.0" encoding="UTF-8"?>
<!DOCTYPE mapper PUBLIC "-//mybatis.org//DTD Mapper 3.0//EN" "http://mybatis.org/dtd/mybatis-3-mapper.dtd">
<mapper namespace="dao.VehicleMapper">
  <resultMap id="BaseResultMap" type="model.Vehicle">
    <!--
      WARNING - @mbg.generated
      This element is automatically generated by MyBatis Generator, do not modify.
    -->
    <id column="vehicle_id" jdbcType="VARCHAR" property="vehicleId" />
    <result column="vehicle_model" jdbcType="VARCHAR" property="vehicleModel" />
    <result column="origin" jdbcType="VARCHAR" property="origin" />
    <result column="route_number" jdbcType="VARCHAR" property="routeNumber" />
    <result column="date" jdbcType="TIMESTAMP" property="date" />
    <result column="purchase_date" jdbcType="TIMESTAMP" property="purchaseDate" />
    <result column="notes" jdbcType="VARCHAR" property="notes" />
  </resultMap>
  <delete id="deleteByPrimaryKey" parameterType="java.lang.String">
    <!--
      WARNING - @mbg.generated
      This element is automatically generated by MyBatis Generator, do not modify.
    -->
    delete from vehicle
    where vehicle_id = #{vehicleId,jdbcType=VARCHAR}
  </delete>
  <insert id="insert" parameterType="model.Vehicle">
    <!--
      WARNING - @mbg.generated
      This element is automatically generated by MyBatis Generator, do not modify.
    -->
    insert into vehicle (vehicle_id, vehicle_model, origin, 
      route_number, date, purchase_date, 
      notes)
    values (#{vehicleId,jdbcType=VARCHAR}, #{vehicleModel,jdbcType=VARCHAR}, #{origin,jdbcType=VARCHAR}, 
      #{routeNumber,jdbcType=VARCHAR}, #{date,jdbcType=TIMESTAMP}, #{purchaseDate,jdbcType=TIMESTAMP}, 
      #{notes,jdbcType=VARCHAR})
  </insert>
  <update id="updateByPrimaryKey" parameterType="model.Vehicle">
    <!--
      WARNING - @mbg.generated
      This element is automatically generated by MyBatis Generator, do not modify.
    -->
    update vehicle
    set vehicle_model = #{vehicleModel,jdbcType=VARCHAR},
      origin = #{origin,jdbcType=VARCHAR},
      route_number = #{routeNumber,jdbcType=VARCHAR},
      date = #{date,jdbcType=TIMESTAMP},
      purchase_date = #{purchaseDate,jdbcType=TIMESTAMP},
      notes = #{notes,jdbcType=VARCHAR}
    where vehicle_id = #{vehicleId,jdbcType=VARCHAR}
  </update>
  <select id="selectByPrimaryKey" parameterType="java.lang.String" resultMap="BaseResultMap">
    <!--
      WARNING - @mbg.generated
      This element is automatically generated by MyBatis Generator, do not modify.
    -->
    select vehicle_id, vehicle_model, origin, route_number, date, purchase_date, notes
    from vehicle
    where vehicle_id = #{vehicleId,jdbcType=VARCHAR}
  </select>
  <select id="selectAll" resultMap="BaseResultMap">
    <!--
      WARNING - @mbg.generated
      This element is automatically generated by MyBatis Generator, do not modify.
    -->
    select vehicle_id, vehicle_model, origin, route_number, date, purchase_date, notes
    from vehicle
  </select>
</mapper>